[
  {
    "id": "167",
    "nome": "Capim FC",
    "link": "/pt/times/167-capim-fc",
    "presidentes": [
      "Jon Vlogs",
      "Luva de Pedreiro"
    ],
    "staffCompleto": "Jon Vlogs + Luva de Pedreiro",
    "jogadores": []
  },
  {
    "id": "161",
    "nome": "Dendele FC",
    "link": "/pt/times/161-dendele-fc",
    "presidentes": [
      "Paulinho o Loko",
      "LuquEt4"
    ],
    "staffCompleto": "Paulinho o Loko + LuquEt4",
    "jogadores": []
  },
  {
    "id": "168",
    "nome": "DesimpaiN",
    "link": "/pt/times/168-desimpain",
    "presidentes": [
      "Renato Vicente"
    ],
    "staffCompleto": "Renato Vicente",
    "jogadores": []
  },
  {
    "id": "220",
    "nome": "Dibrados FC",
    "link": "/pt/times/220-dibrados-fc",
    "presidentes": [
      "Allan Stag",
      "Lucas Tylty"
    ],
    "staffCompleto": "Allan Stag + Lucas Tylty",
    "jogadores": []
  },
  {
    "id": "160",
    "nome": "Fluxo FC",
    "link": "/pt/times/160-fluxo-fc",
    "presidentes": [
      "Cerol",
      "Nobru",
      "Toguro"
    ],
    "staffCompleto": "Cerol + Nobru + Toguro",
    "jogadores": []
  },
  {
    "id": "50",
    "nome": "Furia FC",
    "link": "/pt/times/50-furia-fc",
    "presidentes": [
      "Neymar",
      "Cris Guedes"
    ],
    "staffCompleto": "Neymar + Cris Guedes",
    "jogadores": []
  },
  {
    "id": "49",
    "nome": "G3X FC",
    "link": "/pt/times/49-g3x-fc",
    "presidentes": [
      "Gaules",
      "Kelvin"
    ],
    "staffCompleto": "Gaules + Kelvin",
    "jogadores": []
  },
  {
    "id": "162",
    "nome": "LOUD SC",
    "link": "/pt/times/162-loud-sc",
    "presidentes": [
      "Coringa",
      "Brabox"
    ],
    "staffCompleto": "Coringa + Brabox",
    "jogadores": []
  },
  {
    "id": "163",
    "nome": "Nyvelados FC",
    "link": "/pt/times/163-nyvelados-fc",
    "presidentes": [
      "Nyvi Estephan",
      "Falcão"
    ],
    "staffCompleto": "Nyvi Estephan + Falcão",
    "jogadores": []
  },
  {
    "id": "164",
    "nome": "Podpah Funkbol Clube",
    "link": "/pt/times/164-podpah-funkbol-clube",
    "presidentes": [
      "Igão",
      "Michel Elias",
      "MC Hariel"
    ],
    "staffCompleto": "Igão + Michel Elias + MC Hariel",
    "jogadores": []
  }
]